pptx-stubs/__init__.pyi
pptx-stubs/chart/__init__.pyi
pptx-stubs/chart/axis.pyi
pptx-stubs/chart/category.pyi
pptx-stubs/chart/chart.pyi
pptx-stubs/chart/data.pyi
pptx-stubs/chart/datalabel.pyi
pptx-stubs/chart/legend.pyi
pptx-stubs/chart/marker.pyi
pptx-stubs/chart/plot.pyi
pptx-stubs/chart/point.pyi
pptx-stubs/chart/series.pyi
pptx-stubs/chart/xlsx.pyi
pptx-stubs/chart/xmlwriter.pyi
pptx-stubs/dml/__init__.pyi
pptx-stubs/dml/chtfmt.pyi
pptx-stubs/dml/color.pyi
pptx-stubs/dml/effect.pyi
pptx-stubs/dml/line.pyi
pptx-stubs/parts/__init__.pyi
pptx-stubs/parts/chart.pyi
pptx-stubs/parts/coreprops.pyi
pptx-stubs/parts/embeddedpackage.pyi
pptx-stubs/parts/image.pyi
pptx-stubs/parts/media.pyi
pptx-stubs/parts/presentation.pyi
pptx-stubs/parts/slide.pyi
pptx-stubs/text/__init__.pyi
pptx-stubs/text/fonts.pyi
pptx-stubs/text/layout.pyi
pptx-stubs/text/text.pyi
python_pptx_stubs-1.0.2.dist-info/WHEEL
python_pptx_stubs-1.0.2.dist-info/METADATA
python_pptx_stubs-1.0.2.dist-info/RECORD
