Metadata-Version: 2.4
Name: python-pptx-stubs
Version: 1.0.2
Summary: Type stubs for python-pptx package
Author: Avishrant Sharma
Author-email: Avishrant Sharma <avishrants@gmail.com>
License-Expression: MIT
Classifier: Typing :: Stubs Only
Classifier: Programming Language :: Python :: 3
Requires-Dist: python-pptx==1.0.2
Requires-Python: >=3.12
